etc/default/mongodb-audit-uploader
mongodb_audit_uploader-0.0.1.6.data/scripts/mongodb-auditor-uploader
mongodb_audit_uploader-0.0.1.6.dist-info/DESCRIPTION.rst
mongodb_audit_uploader-0.0.1.6.dist-info/METADATA
mongodb_audit_uploader-0.0.1.6.dist-info/metadata.json
mongodb_audit_uploader-0.0.1.6.dist-info/RECORD
mongodb_audit_uploader-0.0.1.6.dist-info/top_level.txt
mongodb_audit_uploader-0.0.1.6.dist-info/WHEEL
mongodb_auditor_uploader/__init__.py
