Metadata-Version: 2.0
Name: mongodb-audit-uploader
Version: 0.0.1.6
Summary: Upload MongoDB 
Home-page: https://github.com/bookmd/mongodb-audit-uploader
Author: Ben Waters
Author-email: ben@book-md.com
License: MIT
Platform: UNKNOWN
Requires-Dist: elasticsearch
